breathe/__init__.py
breathe/elements/__init__.py
breathe/elements/bound_compound.py
breathe/elements/command_context.py
breathe/elements/commands_ref.py
breathe/elements/true_context.py
breathe/grammar/__init__.py
breathe/grammar/helpers.py
breathe/grammar/master.py
breathe/grammar/subgrammar.py
breathe/rules/__init__.py
breathe/rules/context_switcher.py
breathe/rules/simple_rule.py
dfly_breathe-0.2.4.dist-info/LICENSE.txt
dfly_breathe-0.2.4.dist-info/METADATA
dfly_breathe-0.2.4.dist-info/WHEEL
dfly_breathe-0.2.4.dist-info/top_level.txt
dfly_breathe-0.2.4.dist-info/RECORD
