Metadata-Version: 2.1
Name: dfly-breathe
Version: 0.2.4
Summary: Dragonfly command API
Home-page: https://github.com/mrob95/Breathe
Author: Mike Roberts
Author-email: mike.roberts.2k10@googlemail.com
License: LICENSE.txt
Platform: UNKNOWN
Classifier: Environment :: Win32 (MS Windows)
Classifier: Environment :: X11 Applications
Classifier: Development Status :: 3 - Alpha
Classifier: License :: OSI Approved :: GNU Library or Lesser General Public License (LGPL)
Classifier: Operating System :: Microsoft :: Windows
Classifier: Programming Language :: Python :: 2.7
Classifier: Programming Language :: Python :: 3.7
Requires-Dist: dragonfly2
